[{"__symbolic":"module","version":4,"metadata":{"MomentDateModule":{"__symbolic":"class","decorators":[{"__symbolic":"call","expression":{"__symbolic":"reference","module":"@angular/core","name":"NgModule","line":16,"character":1},"arguments":[{"providers":[{"provide":{"__symbolic":"reference","module":"@angular/material/core","name":"DateAdapter","line":19,"character":15},"useClass":{"__symbolic":"reference","module":"./moment-date-adapter","name":"MomentDateAdapter","line":20,"character":16},"deps":[{"__symbolic":"reference","module":"@angular/material/core","name":"MAT_DATE_LOCALE","line":21,"character":13},{"__symbolic":"reference","module":"./moment-date-adapter","name":"MAT_MOMENT_DATE_ADAPTER_OPTIONS","line":21,"character":30}]}]}]}]},"ɵ0":{"__symbolic":"reference","module":"./moment-date-formats","name":"MAT_MOMENT_DATE_FORMATS"},"MatMomentDateModule":{"__symbolic":"class","decorators":[{"__symbolic":"call","expression":{"__symbolic":"reference","module":"@angular/core","name":"NgModule","line":28,"character":1},"arguments":[{"imports":[{"__symbolic":"reference","name":"MomentDateModule"}],"providers":[{"provide":{"__symbolic":"reference","module":"@angular/material/core","name":"MAT_DATE_FORMATS","line":30,"character":24},"useValue":{"__symbolic":"reference","name":"ɵ0"}}]}]}]}},"exports":[{"from":"./moment-date-adapter"},{"from":"./moment-date-formats"}]}]