[{"__symbolic":"module","version":4,"metadata":{"DialogContentExample":{"__symbolic":"class","decorators":[{"__symbolic":"call","expression":{"__symbolic":"reference","module":"@angular/core","name":"Component","line":6,"character":1},"arguments":[{"selector":"dialog-content-example","templateUrl":"dialog-content-example.html","styleUrls":["dialog-content-example.css"]}]}],"members":{"__ctor__":[{"__symbolic":"constructor","parameters":[{"__symbolic":"reference","module":"@angular/material","name":"MatDialog","line":12,"character":29}]}],"openDialog":[{"__symbolic":"method"}]}},"DialogContentExampleDialog":{"__symbolic":"class","decorators":[{"__symbolic":"call","expression":{"__symbolic":"reference","module":"@angular/core","name":"Component","line":23,"character":1},"arguments":[{"selector":"dialog-content-example-dialog","templateUrl":"dialog-content-example-dialog.html"}]}]}}}]