[{"__symbolic":"module","version":4,"metadata":{"DataSource":{"__symbolic":"class","arity":1,"members":{"connect":[{"__symbolic":"method"}],"disconnect":[{"__symbolic":"method"}]}},"isDataSource":{"__symbolic":"function","parameters":["value"],"value":{"__symbolic":"binop","operator":"&&","left":{"__symbolic":"reference","name":"value"},"right":{"__symbolic":"binop","operator":"===","left":{"__symbolic":"error","message":"Expression form not supported","line":37,"character":18},"right":"function"}}}},"importAs":"@angular/cdk/collections"}]