[{"__symbolic":"module","version":4,"metadata":{"MatSidenavContent":{"__symbolic":"class","extends":{"__symbolic":"reference","module":"./drawer","name":"MatDrawerContent","line":40,"character":39},"decorators":[{"__symbolic":"call","expression":{"__symbolic":"reference","module":"@angular/core","name":"Component","line":28,"character":1},"arguments":[{"moduleId":{"__symbolic":"select","expression":{"__symbolic":"reference","name":"module"},"member":"id"},"selector":"mat-sidenav-content","template":"<ng-content></ng-content>","host":{"class":"mat-drawer-content mat-sidenav-content","[style.margin-left.px]":"_container._contentMargins.left","[style.margin-right.px]":"_container._contentMargins.right","$quoted$":["class","[style.margin-left.px]","[style.margin-right.px]"]},"changeDetection":{"__symbolic":"select","expression":{"__symbolic":"reference","module":"@angular/core","name":"ChangeDetectionStrategy","line":37,"character":19},"member":"OnPush"},"encapsulation":{"__symbolic":"select","expression":{"__symbolic":"reference","module":"@angular/core","name":"ViewEncapsulation","line":38,"character":17},"member":"None"}}]}],"members":{"__ctor__":[{"__symbolic":"constructor","parameterDecorators":[null,[{"__symbolic":"call","expression":{"__symbolic":"reference","module":"@angular/core","name":"Inject","line":43,"character":7},"arguments":[{"__symbolic":"reference","name":"MatSidenavContainer"}]}],null,null,null],"parameters":[{"__symbolic":"reference","module":"@angular/core","name":"ChangeDetectorRef","line":42,"character":25},{"__symbolic":"reference","name":"MatSidenavContainer"},{"__symbolic":"reference","module":"@angular/core","name":"ElementRef","line":44,"character":18,"arguments":[{"__symbolic":"error","message":"Could not resolve type","line":44,"character":29,"context":{"typeName":"HTMLElement"}}]},{"__symbolic":"reference","module":"@angular/cdk/scrolling","name":"ScrollDispatcher","line":45,"character":24},{"__symbolic":"reference","module":"@angular/core","name":"NgZone","line":46,"character":14}]}]}},"MatSidenav":{"__symbolic":"class","extends":{"__symbolic":"reference","module":"./drawer","name":"MatDrawer","line":77,"character":32},"decorators":[{"__symbolic":"call","expression":{"__symbolic":"reference","module":"@angular/core","name":"Component","line":52,"character":1},"arguments":[{"moduleId":{"__symbolic":"select","expression":{"__symbolic":"reference","name":"module"},"member":"id"},"selector":"mat-sidenav","exportAs":"matSidenav","templateUrl":"drawer.html","animations":[{"__symbolic":"select","expression":{"__symbolic":"reference","module":"./drawer-animations","name":"matDrawerAnimations","line":57,"character":15},"member":"transformDrawer"}],"host":{"class":"mat-drawer mat-sidenav","tabIndex":"-1","[@transform]":"_animationState","(@transform.start)":"_animationStarted.next($event)","(@transform.done)":"_animationEnd.next($event)","[attr.align]":"null","[class.mat-drawer-end]":"position === \"end\"","[class.mat-drawer-over]":"mode === \"over\"","[class.mat-drawer-push]":"mode === \"push\"","[class.mat-drawer-side]":"mode === \"side\"","[class.mat-sidenav-fixed]":"fixedInViewport","[style.top.px]":"fixedInViewport ? fixedTopGap : null","[style.bottom.px]":"fixedInViewport ? fixedBottomGap : null","$quoted$":["class","tabIndex","[@transform]","(@transform.start)","(@transform.done)","[attr.align]","[class.mat-drawer-end]","[class.mat-drawer-over]","[class.mat-drawer-push]","[class.mat-drawer-side]","[class.mat-sidenav-fixed]","[style.top.px]","[style.bottom.px]"]},"changeDetection":{"__symbolic":"select","expression":{"__symbolic":"reference","module":"@angular/core","name":"ChangeDetectionStrategy","line":74,"character":19},"member":"OnPush"},"encapsulation":{"__symbolic":"select","expression":{"__symbolic":"reference","module":"@angular/core","name":"ViewEncapsulation","line":75,"character":17},"member":"None"}}]}],"members":{"fixedInViewport":[{"__symbolic":"property","decorators":[{"__symbolic":"call","expression":{"__symbolic":"reference","module":"@angular/core","name":"Input","line":79,"character":3}}]}],"fixedTopGap":[{"__symbolic":"property","decorators":[{"__symbolic":"call","expression":{"__symbolic":"reference","module":"@angular/core","name":"Input","line":88,"character":3}}]}],"fixedBottomGap":[{"__symbolic":"property","decorators":[{"__symbolic":"call","expression":{"__symbolic":"reference","module":"@angular/core","name":"Input","line":97,"character":3}}]}]}},"MatSidenavContainer":{"__symbolic":"class","extends":{"__symbolic":"reference","module":"./drawer","name":"MatDrawerContainer","line":117,"character":41},"decorators":[{"__symbolic":"call","expression":{"__symbolic":"reference","module":"@angular/core","name":"Component","line":104,"character":1},"arguments":[{"moduleId":{"__symbolic":"select","expression":{"__symbolic":"reference","name":"module"},"member":"id"},"selector":"mat-sidenav-container","exportAs":"matSidenavContainer","templateUrl":"sidenav-container.html","styleUrls":["drawer.css"],"host":{"class":"mat-drawer-container mat-sidenav-container","[class.mat-drawer-container-explicit-backdrop]":"_backdropOverride","$quoted$":["class","[class.mat-drawer-container-explicit-backdrop]"]},"changeDetection":{"__symbolic":"select","expression":{"__symbolic":"reference","module":"@angular/core","name":"ChangeDetectionStrategy","line":114,"character":19},"member":"OnPush"},"encapsulation":{"__symbolic":"select","expression":{"__symbolic":"reference","module":"@angular/core","name":"ViewEncapsulation","line":115,"character":17},"member":"None"}}]}],"members":{"_drawers":[{"__symbolic":"property","decorators":[{"__symbolic":"call","expression":{"__symbolic":"reference","module":"@angular/core","name":"ContentChildren","line":118,"character":3},"arguments":[{"__symbolic":"reference","name":"MatSidenav"}]}]}],"_content":[{"__symbolic":"property","decorators":[{"__symbolic":"call","expression":{"__symbolic":"reference","module":"@angular/core","name":"ContentChild","line":119,"character":3},"arguments":[{"__symbolic":"reference","name":"MatSidenavContent"}]}]}]}}},"importAs":"@angular/material/sidenav"}]